anilisthelper/__init__.py
anilisthelper/anilist_helper.py
anilisthelper/token_generator.py
anilisthelper/token_getter.html
anilist_helper-1.42.dist-info/LICENSE
anilist_helper-1.42.dist-info/METADATA
anilist_helper-1.42.dist-info/WHEEL
anilist_helper-1.42.dist-info/top_level.txt
anilist_helper-1.42.dist-info/RECORD
