Metadata-Version: 2.1
Name: anilist-helper
Version: 1.42
Summary: A simple library to help you fetch data from AniList.
Author: Dominik Procházka
Maintainer: Dominik Procházka
Project-URL: Homepage, https://github.com/ProchyGaming/anilist-helper
Project-URL: Documentation, https://github.com/ProchyGaming/anilist-helper/wiki
Project-URL: Source, https://github.com/ProchyGaming/anilist-helper
Keywords: python,anilist
Classifier: Development Status :: 5 - Production/Stable
Classifier: Framework :: Flask
Classifier: Topic :: Database
Classifier: Topic :: Games/Entertainment
Classifier: License :: OSI Approved :: GNU General Public License v3 or later (GPLv3+)
Classifier: Programming Language :: Python :: 3.8
Classifier: Programming Language :: Python :: 3.9
Classifier: Programming Language :: Python :: 3.10
Classifier: Programming Language :: Python :: 3.11
Classifier: Programming Language :: Python :: 3.12
Requires-Python: >=3.8
License-File: LICENSE
Requires-Dist: requests
Requires-Dist: flask
Requires-Dist: gevent
